[{"bandwidth_kbps": 2498.9828178694156, "duration_ms": 18.0, "latency_ms": 20}, {"bandwidth_kbps": 2498.9828178694156, "duration_ms": 582.0, "latency_ms": 20}, {"bandwidth_kbps": 2524.6247464503044, "duration_ms": 116.0, "latency_ms": 20}, {"bandwidth_kbps": 2524.6247464503044, "duration_ms": 493.0, "latency_ms": 20}, {"bandwidth_kbps": 2514.2831460674156, "duration_ms": 112.0, "latency_ms": 20}, {"bandwidth_kbps": 2514.2831460674156, "duration_ms": 445.0, "latency_ms": 20}, {"bandwidth_kbps": 2522.2231237322517, "duration_ms": 49.0, "latency_ms": 20}, {"bandwidth_kbps": 2522.2231237322517, "duration_ms": 493.0, "latency_ms": 20}, {"bandwidth_kbps": 2471.837837837838, "duration_ms": 118.0, "latency_ms": 20}, {"bandwidth_kbps": 2471.837837837838, "duration_ms": 1332.0, "latency_ms": 20}, {"bandwidth_kbps": 2462.899308224443, "duration_ms": 63.0, "latency_ms": 20}, {"bandwidth_kbps": 2462.899308224443, "duration_ms": 2602.0, "latency_ms": 20}, {"bandwidth_kbps": 2460.6385869565215, "duration_ms": 91.0, "latency_ms": 20}, {"bandwidth_kbps": 2460.6385869565215, "duration_ms": 2944.0, "latency_ms": 20}, {"bandwidth_kbps": 2891.580095432856, "duration_ms": 57.0, "latency_ms": 20}, {"bandwidth_kbps": 2891.580095432856, "duration_ms": 2934.0, "latency_ms": 20}, {"bandwidth_kbps": 3948.300925925926, "duration_ms": 61.0, "latency_ms": 20}, {"bandwidth_kbps": 3948.300925925926, "duration_ms": 1728.0, "latency_ms": 20}, {"bandwidth_kbps": 3540.107711138311, "duration_ms": 71.0, "latency_ms": 20}, {"bandwidth_kbps": 3540.107711138311, "duration_ms": 4902.0, "latency_ms": 20}, {"bandwidth_kbps": 3716.216285531096, "duration_ms": 98.0, "latency_ms": 20}, {"bandwidth_kbps": 3716.216285531096, "duration_ms": 4679.0, "latency_ms": 20}, {"bandwidth_kbps": 4058.7876447876447, "duration_ms": 123.0, "latency_ms": 20}, {"bandwidth_kbps": 4058.7876447876447, "duration_ms": 4144.0, "latency_ms": 20}, {"bandwidth_kbps": 3808.598146951088, "duration_ms": 53.0, "latency_ms": 20}, {"bandwidth_kbps": 3808.598146951088, "duration_ms": 4641.0, "latency_ms": 20}, {"bandwidth_kbps": 3525.6649234940924, "duration_ms": 65.0, "latency_ms": 20}, {"bandwidth_kbps": 3525.6649234940924, "duration_ms": 5163.0, "latency_ms": 20}, {"bandwidth_kbps": 3972.070314434266, "duration_ms": 36.0, "latency_ms": 20}, {"bandwidth_kbps": 3972.070314434266, "duration_ms": 4039.0, "latency_ms": 20}, {"bandwidth_kbps": 3988.8496641186007, "duration_ms": 58.0, "latency_ms": 20}, {"bandwidth_kbps": 3988.8496641186007, "duration_ms": 4317.0, "latency_ms": 20}, {"bandwidth_kbps": 3943.49020452099, "duration_ms": 85.0, "latency_ms": 20}, {"bandwidth_kbps": 3943.49020452099, "duration_ms": 4645.0, "latency_ms": 20}, {"bandwidth_kbps": 3847.7571228397946, "duration_ms": 248.0, "latency_ms": 20}, {"bandwidth_kbps": 3847.7571228397946, "duration_ms": 4282.0, "latency_ms": 20}, {"bandwidth_kbps": 3951.4697508896797, "duration_ms": 127.0, "latency_ms": 20}, {"bandwidth_kbps": 3951.4697508896797, "duration_ms": 4496.0, "latency_ms": 20}, {"bandwidth_kbps": 3977.3702166897187, "duration_ms": 104.0, "latency_ms": 20}, {"bandwidth_kbps": 3977.3702166897187, "duration_ms": 4338.0, "latency_ms": 20}, {"bandwidth_kbps": 3993.681840430739, "duration_ms": 60.0, "latency_ms": 20}, {"bandwidth_kbps": 3993.681840430739, "duration_ms": 4086.0, "latency_ms": 20}, {"bandwidth_kbps": 4006.385641969627, "duration_ms": 113.0, "latency_ms": 20}, {"bandwidth_kbps": 4006.385641969627, "duration_ms": 4346.0, "latency_ms": 20}, {"bandwidth_kbps": 3971.407374301676, "duration_ms": 52.0, "latency_ms": 20}, {"bandwidth_kbps": 3971.407374301676, "duration_ms": 4475.0, "latency_ms": 20}, {"bandwidth_kbps": 4000.146771037182, "duration_ms": 128.0, "latency_ms": 20}, {"bandwidth_kbps": 4000.146771037182, "duration_ms": 4088.0, "latency_ms": 20}, {"bandwidth_kbps": 4007.8625429553263, "duration_ms": 110.0, "latency_ms": 20}, {"bandwidth_kbps": 4007.8625429553263, "duration_ms": 4365.0, "latency_ms": 20}, {"bandwidth_kbps": 4036.8763183125598, "duration_ms": 36.0, "latency_ms": 20}, {"bandwidth_kbps": 4036.8763183125598, "duration_ms": 4172.0, "latency_ms": 20}, {"bandwidth_kbps": 4049.1662793154446, "duration_ms": 319.0, "latency_ms": 20}, {"bandwidth_kbps": 4049.1662793154446, "duration_ms": 4733.0, "latency_ms": 20}, {"bandwidth_kbps": 4049.3798767967146, "duration_ms": 76.0, "latency_ms": 20}, {"bandwidth_kbps": 4049.3798767967146, "duration_ms": 3896.0, "latency_ms": 20}, {"bandwidth_kbps": 4045.7029140014215, "duration_ms": 102.0, "latency_ms": 20}, {"bandwidth_kbps": 4045.7029140014215, "duration_ms": 4221.0, "latency_ms": 20}, {"bandwidth_kbps": 4041.344537815126, "duration_ms": 83.0, "latency_ms": 20}, {"bandwidth_kbps": 4041.344537815126, "duration_ms": 4284.0, "latency_ms": 20}, {"bandwidth_kbps": 4043.421191102607, "duration_ms": 113.0, "latency_ms": 20}, {"bandwidth_kbps": 4043.421191102607, "duration_ms": 4181.0, "latency_ms": 20}, {"bandwidth_kbps": 3933.7948717948716, "duration_ms": 118.0, "latency_ms": 20}, {"bandwidth_kbps": 3933.7948717948716, "duration_ms": 4368.0, "latency_ms": 20}, {"bandwidth_kbps": 3875.4348883484413, "duration_ms": 30.0, "latency_ms": 20}, {"bandwidth_kbps": 3875.4348883484413, "duration_ms": 4523.0, "latency_ms": 20}, {"bandwidth_kbps": 3959.7593073593075, "duration_ms": 79.0, "latency_ms": 20}, {"bandwidth_kbps": 3959.7593073593075, "duration_ms": 4620.0, "latency_ms": 20}, {"bandwidth_kbps": 3992.71107266436, "duration_ms": 81.0, "latency_ms": 20}, {"bandwidth_kbps": 3992.71107266436, "duration_ms": 4624.0, "latency_ms": 20}, {"bandwidth_kbps": 4020.530707923113, "duration_ms": 268.0, "latency_ms": 20}, {"bandwidth_kbps": 4020.530707923113, "duration_ms": 4266.0, "latency_ms": 20}, {"bandwidth_kbps": 4019.431562418215, "duration_ms": 42.0, "latency_ms": 20}, {"bandwidth_kbps": 4019.431562418215, "duration_ms": 3821.0, "latency_ms": 20}, {"bandwidth_kbps": 4021.4737827715358, "duration_ms": 78.0, "latency_ms": 20}, {"bandwidth_kbps": 4021.4737827715358, "duration_ms": 4272.0, "latency_ms": 20}, {"bandwidth_kbps": 3974.4778567523235, "duration_ms": 134.0, "latency_ms": 20}, {"bandwidth_kbps": 3974.4778567523235, "duration_ms": 1829.0, "latency_ms": 20}, {"bandwidth_kbps": 3957.7969165337586, "duration_ms": 65.0, "latency_ms": 20}, {"bandwidth_kbps": 3957.7969165337586, "duration_ms": 1881.0, "latency_ms": 20}, {"bandwidth_kbps": 3958.270893371758, "duration_ms": 119.0, "latency_ms": 20}, {"bandwidth_kbps": 3958.270893371758, "duration_ms": 1735.0, "latency_ms": 20}, {"bandwidth_kbps": 3980.9949886104782, "duration_ms": 66.0, "latency_ms": 20}, {"bandwidth_kbps": 3980.9949886104782, "duration_ms": 4390.0, "latency_ms": 20}, {"bandwidth_kbps": 4019.7546767700687, "duration_ms": 111.0, "latency_ms": 20}, {"bandwidth_kbps": 4019.7546767700687, "duration_ms": 4223.0, "latency_ms": 20}, {"bandwidth_kbps": 4031.981830570066, "duration_ms": 78.0, "latency_ms": 20}, {"bandwidth_kbps": 4031.981830570066, "duration_ms": 4403.0, "latency_ms": 20}, {"bandwidth_kbps": 4028.341232227488, "duration_ms": 286.0, "latency_ms": 20}, {"bandwidth_kbps": 4028.341232227488, "duration_ms": 4220.0, "latency_ms": 20}, {"bandwidth_kbps": 3723.2334783509427, "duration_ms": 86.0, "latency_ms": 20}, {"bandwidth_kbps": 3723.2334783509427, "duration_ms": 4827.0, "latency_ms": 20}, {"bandwidth_kbps": 3808.9633406166545, "duration_ms": 78.0, "latency_ms": 20}, {"bandwidth_kbps": 3808.9633406166545, "duration_ms": 4119.0, "latency_ms": 20}, {"bandwidth_kbps": 4023.359626604434, "duration_ms": 80.0, "latency_ms": 20}, {"bandwidth_kbps": 4023.359626604434, "duration_ms": 4285.0, "latency_ms": 20}, {"bandwidth_kbps": 3847.4552163703456, "duration_ms": 115.0, "latency_ms": 20}, {"bandwidth_kbps": 3847.4552163703456, "duration_ms": 2981.0, "latency_ms": 20}]