[{"bandwidth_kbps": 2703.360594795539, "duration_ms": 14.0, "latency_ms": 20}, {"bandwidth_kbps": 2703.360594795539, "duration_ms": 538.0, "latency_ms": 20}, {"bandwidth_kbps": 4020.9564393939395, "duration_ms": 95.0, "latency_ms": 20}, {"bandwidth_kbps": 4020.9564393939395, "duration_ms": 4224.0, "latency_ms": 20}, {"bandwidth_kbps": 3279.8436810589346, "duration_ms": 39.0, "latency_ms": 20}, {"bandwidth_kbps": 3279.8436810589346, "duration_ms": 3173.0, "latency_ms": 20}, {"bandwidth_kbps": 4526.329735764793, "duration_ms": 125.0, "latency_ms": 20}, {"bandwidth_kbps": 4526.329735764793, "duration_ms": 2687.0, "latency_ms": 20}, {"bandwidth_kbps": 3230.0507111935685, "duration_ms": 123.0, "latency_ms": 20}, {"bandwidth_kbps": 3230.0507111935685, "duration_ms": 1617.0, "latency_ms": 20}, {"bandwidth_kbps": 4622.029259084474, "duration_ms": 73.0, "latency_ms": 20}, {"bandwidth_kbps": 4622.029259084474, "duration_ms": 2119.0, "latency_ms": 20}, {"bandwidth_kbps": 4257.2725182062095, "duration_ms": 82.0, "latency_ms": 20}, {"bandwidth_kbps": 4257.2725182062095, "duration_ms": 2609.0, "latency_ms": 20}, {"bandwidth_kbps": 4102.050062578222, "duration_ms": 90.0, "latency_ms": 20}, {"bandwidth_kbps": 4102.050062578222, "duration_ms": 3196.0, "latency_ms": 20}, {"bandwidth_kbps": 6436.475471698113, "duration_ms": 100.0, "latency_ms": 20}, {"bandwidth_kbps": 6436.475471698113, "duration_ms": 1060.0, "latency_ms": 20}, {"bandwidth_kbps": 5825.580876494024, "duration_ms": 38.0, "latency_ms": 20}, {"bandwidth_kbps": 5825.580876494024, "duration_ms": 1255.0, "latency_ms": 20}, {"bandwidth_kbps": 4349.218609304652, "duration_ms": 51.0, "latency_ms": 20}, {"bandwidth_kbps": 4349.218609304652, "duration_ms": 3998.0, "latency_ms": 20}, {"bandwidth_kbps": 4573.033170201196, "duration_ms": 293.0, "latency_ms": 20}, {"bandwidth_kbps": 4573.033170201196, "duration_ms": 3678.0, "latency_ms": 20}, {"bandwidth_kbps": 4845.313596491228, "duration_ms": 131.0, "latency_ms": 20}, {"bandwidth_kbps": 4845.313596491228, "duration_ms": 3648.0, "latency_ms": 20}, {"bandwidth_kbps": 5169.840386253905, "duration_ms": 54.0, "latency_ms": 20}, {"bandwidth_kbps": 5169.840386253905, "duration_ms": 3521.0, "latency_ms": 20}, {"bandwidth_kbps": 5367.411174305788, "duration_ms": 78.0, "latency_ms": 20}, {"bandwidth_kbps": 5367.411174305788, "duration_ms": 2989.0, "latency_ms": 20}, {"bandwidth_kbps": 5621.894874306236, "duration_ms": 112.0, "latency_ms": 20}, {"bandwidth_kbps": 5621.894874306236, "duration_ms": 3063.0, "latency_ms": 20}, {"bandwidth_kbps": 5357.564200058497, "duration_ms": 35.0, "latency_ms": 20}, {"bandwidth_kbps": 5357.564200058497, "duration_ms": 3419.0, "latency_ms": 20}, {"bandwidth_kbps": 5195.867549668874, "duration_ms": 81.0, "latency_ms": 20}, {"bandwidth_kbps": 5195.867549668874, "duration_ms": 3171.0, "latency_ms": 20}, {"bandwidth_kbps": 5267.064334420397, "duration_ms": 127.0, "latency_ms": 20}, {"bandwidth_kbps": 5267.064334420397, "duration_ms": 3373.0, "latency_ms": 20}, {"bandwidth_kbps": 5181.330930930931, "duration_ms": 128.0, "latency_ms": 20}, {"bandwidth_kbps": 5181.330930930931, "duration_ms": 3330.0, "latency_ms": 20}, {"bandwidth_kbps": 5525.968167964782, "duration_ms": 262.0, "latency_ms": 20}, {"bandwidth_kbps": 5525.968167964782, "duration_ms": 2953.0, "latency_ms": 20}, {"bandwidth_kbps": 5310.079902409271, "duration_ms": 53.0, "latency_ms": 20}, {"bandwidth_kbps": 5310.079902409271, "duration_ms": 3279.0, "latency_ms": 20}, {"bandwidth_kbps": 3074.7487889273357, "duration_ms": 123.0, "latency_ms": 20}, {"bandwidth_kbps": 3074.7487889273357, "duration_ms": 5780.0, "latency_ms": 20}, {"bandwidth_kbps": 3669.7935368043086, "duration_ms": 129.0, "latency_ms": 20}, {"bandwidth_kbps": 3669.7935368043086, "duration_ms": 4456.0, "latency_ms": 20}, {"bandwidth_kbps": 4804.8118648722875, "duration_ms": 33.0, "latency_ms": 20}, {"bandwidth_kbps": 4804.8118648722875, "duration_ms": 3641.0, "latency_ms": 20}, {"bandwidth_kbps": 5072.84578313253, "duration_ms": 63.0, "latency_ms": 20}, {"bandwidth_kbps": 5072.84578313253, "duration_ms": 3320.0, "latency_ms": 20}, {"bandwidth_kbps": 5144.8869798657715, "duration_ms": 81.0, "latency_ms": 20}, {"bandwidth_kbps": 5144.8869798657715, "duration_ms": 3725.0, "latency_ms": 20}, {"bandwidth_kbps": 5757.804379562044, "duration_ms": 73.0, "latency_ms": 20}, {"bandwidth_kbps": 5757.804379562044, "duration_ms": 2740.0, "latency_ms": 20}, {"bandwidth_kbps": 2712.343074968234, "duration_ms": 60.0, "latency_ms": 20}, {"bandwidth_kbps": 2712.343074968234, "duration_ms": 6296.0, "latency_ms": 20}, {"bandwidth_kbps": 3143.267973856209, "duration_ms": 300.0, "latency_ms": 20}, {"bandwidth_kbps": 3143.267973856209, "duration_ms": 5508.0, "latency_ms": 20}, {"bandwidth_kbps": 4709.065181058496, "duration_ms": 99.0, "latency_ms": 20}, {"bandwidth_kbps": 4709.065181058496, "duration_ms": 3590.0, "latency_ms": 20}, {"bandwidth_kbps": 4688.353615279672, "duration_ms": 106.0, "latency_ms": 20}, {"bandwidth_kbps": 4688.353615279672, "duration_ms": 3665.0, "latency_ms": 20}, {"bandwidth_kbps": 4479.578839764887, "duration_ms": 39.0, "latency_ms": 20}, {"bandwidth_kbps": 4479.578839764887, "duration_ms": 3913.0, "latency_ms": 20}, {"bandwidth_kbps": 4792.792245218759, "duration_ms": 82.0, "latency_ms": 20}, {"bandwidth_kbps": 4792.792245218759, "duration_ms": 3817.0, "latency_ms": 20}, {"bandwidth_kbps": 5554.240673886883, "duration_ms": 86.0, "latency_ms": 20}, {"bandwidth_kbps": 5554.240673886883, "duration_ms": 3324.0, "latency_ms": 20}, {"bandwidth_kbps": 6062.772711205373, "duration_ms": 75.0, "latency_ms": 20}, {"bandwidth_kbps": 6062.772711205373, "duration_ms": 2829.0, "latency_ms": 20}, {"bandwidth_kbps": 5386.968782883199, "duration_ms": 70.0, "latency_ms": 20}, {"bandwidth_kbps": 5386.968782883199, "duration_ms": 2851.0, "latency_ms": 20}, {"bandwidth_kbps": 5590.542141230068, "duration_ms": 49.0, "latency_ms": 20}, {"bandwidth_kbps": 5590.542141230068, "duration_ms": 3073.0, "latency_ms": 20}, {"bandwidth_kbps": 4564.427807486631, "duration_ms": 318.0, "latency_ms": 20}, {"bandwidth_kbps": 4564.427807486631, "duration_ms": 3740.0, "latency_ms": 20}, {"bandwidth_kbps": 4684.572987721692, "duration_ms": 70.0, "latency_ms": 20}, {"bandwidth_kbps": 4684.572987721692, "duration_ms": 3665.0, "latency_ms": 20}, {"bandwidth_kbps": 4787.944365597502, "duration_ms": 39.0, "latency_ms": 20}, {"bandwidth_kbps": 4787.944365597502, "duration_ms": 3523.0, "latency_ms": 20}, {"bandwidth_kbps": 5404.0098948670375, "duration_ms": 73.0, "latency_ms": 20}, {"bandwidth_kbps": 5404.0098948670375, "duration_ms": 3234.0, "latency_ms": 20}, {"bandwidth_kbps": 4595.404439631835, "duration_ms": 65.0, "latency_ms": 20}, {"bandwidth_kbps": 4595.404439631835, "duration_ms": 3694.0, "latency_ms": 20}, {"bandwidth_kbps": 4245.0540411286465, "duration_ms": 111.0, "latency_ms": 20}, {"bandwidth_kbps": 4245.0540411286465, "duration_ms": 4182.0, "latency_ms": 20}, {"bandwidth_kbps": 4667.655134541461, "duration_ms": 116.0, "latency_ms": 20}, {"bandwidth_kbps": 4667.655134541461, "duration_ms": 3642.0, "latency_ms": 20}, {"bandwidth_kbps": 5183.746178252091, "duration_ms": 58.0, "latency_ms": 20}, {"bandwidth_kbps": 5183.746178252091, "duration_ms": 3467.0, "latency_ms": 20}, {"bandwidth_kbps": 4383.660240290584, "duration_ms": 130.0, "latency_ms": 20}, {"bandwidth_kbps": 4383.660240290584, "duration_ms": 3579.0, "latency_ms": 20}, {"bandwidth_kbps": 3623.3913408995377, "duration_ms": 312.0, "latency_ms": 20}, {"bandwidth_kbps": 3623.3913408995377, "duration_ms": 4758.0, "latency_ms": 20}, {"bandwidth_kbps": 4118.227648114901, "duration_ms": 51.0, "latency_ms": 20}, {"bandwidth_kbps": 4118.227648114901, "duration_ms": 2785.0, "latency_ms": 20}]